mir/anidb/__init__.py
mir/anidb/_xmlns.py
mir/anidb/anime.py
mir/anidb/api.py
mir/anidb/titles.py
mir.anidb-2.0.3.dist-info/LICENSE
mir.anidb-2.0.3.dist-info/METADATA
mir.anidb-2.0.3.dist-info/WHEEL
mir.anidb-2.0.3.dist-info/top_level.txt
mir.anidb-2.0.3.dist-info/RECORD
