Metadata-Version: 2.1
Name: mir.anidb
Version: 2.0.3
Summary: AniDB API
Home-page: https://github.com/darkfeline/mir.anidb
Author: Allen Li
Author-email: darkfeline@felesatra.moe
License: UNKNOWN
Platform: UNKNOWN
Classifier: Development Status :: 5 - Production/Stable
Classifier: Intended Audience :: Developers
Classifier: License :: OSI Approved :: Apache Software License
Classifier: Programming Language :: Python :: 3.6
Requires-Dist: requests (~=2.23.0)
